asix.py
asix-7.7.dist-info/METADATA
asix-7.7.dist-info/WHEEL
asix-7.7.dist-info/top_level.txt
asix-7.7.dist-info/RECORD
