Metadata-Version: 2.2
Name: asix
Version: 7.7
Summary: A collection of utilities for Pygame
Home-page: https://github.com/CoataocCreate/ASIX
Author: Coataoc
Author-email: coataoctrader@gmail.com
Classifier: Programming Language :: Python :: 3
Classifier: License :: OSI Approved :: MIT License
Classifier: Operating System :: OS Independent
Requires-Python: >=3.6
Requires-Dist: pygame>=2.1.0
Requires-Dist: PyOpenGL
Dynamic: author
Dynamic: author-email
Dynamic: classifier
Dynamic: description
Dynamic: description-content-type
Dynamic: home-page
Dynamic: requires-dist
Dynamic: requires-python
Dynamic: summary
